<annotation>
	<folder>collectedimages</folder>
	<filename>tequiero.49e6783b-666e-11f0-92a7-80a55e207f58.jpg</filename>
	<path>C:\Users\ASUS\Desktop\RealTimeObjectDetection\Tensorflow\workspace\images\collectedimages\tequiero.49e6783b-666e-11f0-92a7-80a55e207f58.jpg</path>
	<source>
		<database>Unknown</database>
	</source>
	<size>
		<width>640</width>
		<height>480</height>
		<depth>3</depth>
	</size>
	<segmented>0</segmented>
	<object>
		<name>Te quiero</name>
		<pose>Unspecified</pose>
		<truncated>1</truncated>
		<difficult>0</difficult>
		<bndbox>
			<xmin>312</xmin>
			<ymin>144</ymin>
			<xmax>640</xmax>
			<ymax>453</ymax>
		</bndbox>
	</object>
</annotation>
